crossgui/__init__.py
crossgui-0.0.3.dist-info/LICENSE
crossgui-0.0.3.dist-info/METADATA
crossgui-0.0.3.dist-info/WHEEL
crossgui-0.0.3.dist-info/RECORD
